{
  "source_files": [
    "./data/11.18问卷模拟数据_1000份_严格对齐训练格式.csv",
    "./data/365模拟问卷数据_100份_严格排版.csv",
    "./data/365问卷模拟数据_1000份_严格排版.csv"
  ],
  "n_samples": 2100,
  "global_mean_risk": 0.3841428571428572,
  "items": {
    "家庭沟通分": [
      {
        "value": 0,
        "mean_risk": 0.1292929292929293,
        "count": 198,
        "score": -1.0193997113997115
      },
      {
        "value": 1,
        "mean_risk": 0.1789272030651341,
        "count": 261,
        "score": -0.8208626163108923
      },
      {
        "value": 2,
        "mean_risk": 0.2303448275862069,
        "count": 290,
        "score": -0.6151921182266011
      },
      {
        "value": 3,
        "mean_risk": 0.42411347517730497,
        "count": 141,
        "score": 0.15988247213779117
      },
      {
        "value": 4,
        "mean_risk": 0.5385964912280702,
        "count": 57,
        "score": 0.617814536340852
      },
      {
        "value": 5,
        "mean_risk": 0.5113207547169811,
        "count": 53,
        "score": 0.5087115902964958
      }
    ],
    "家庭冲突分": [
      {
        "value": 0,
        "mean_risk": 0.31824644549763037,
        "count": 422,
        "score": -0.2635856465809072
      },
      {
        "value": 1,
        "mean_risk": 0.32739999999999997,
        "count": 500,
        "score": -0.22697142857142882
      },
      {
        "value": 2,
        "mean_risk": 0.38123980424143555,
        "count": 613,
        "score": -0.011612211605686484
      },
      {
        "value": 3,
        "mean_risk": 0.4729299363057325,
        "count": 314,
        "score": 0.35514831665150126
      },
      {
        "value": 4,
        "mean_risk": 0.5184523809523809,
        "count": 168,
        "score": 0.5372380952380948
      },
      {
        "value": 5,
        "mean_risk": 0.4746987951807229,
        "count": 83,
        "score": 0.36222375215146285
      }
    ],
    "冲动易冲动程度": [
      {
        "value": 0,
        "mean_risk": 0.3256218905472637,
        "count": 402,
        "score": -0.23408386638237388
      },
      {
        "value": 1,
        "mean_risk": 0.3296442687747036,
        "count": 506,
        "score": -0.2179943534726143
      },
      {
        "value": 2,
        "mean_risk": 0.3749603803486529,
        "count": 631,
        "score": -0.03672990717681701
      },
      {
        "value": 3,
        "mean_risk": 0.4671328671328671,
        "count": 286,
        "score": 0.33196003996003975
      },
      {
        "value": 4,
        "mean_risk": 0.5108910891089109,
        "count": 202,
        "score": 0.5069929278642149
      },
      {
        "value": 5,
        "mean_risk": 0.4876712328767123,
        "count": 73,
        "score": 0.4141135029354206
      }
    ],
    "攻击暴力倾向": [
      {
        "value": 0,
        "mean_risk": 0.28006993006993003,
        "count": 572,
        "score": -0.4162917082917086
      },
      {
        "value": 1,
        "mean_risk": 0.3159090909090909,
        "count": 660,
        "score": -0.27293506493506503
      },
      {
        "value": 2,
        "mean_risk": 0.49417249417249415,
        "count": 429,
        "score": 0.4401185481185479
      },
      {
        "value": 3,
        "mean_risk": 0.516822429906542,
        "count": 214,
        "score": 0.5307182910547394
      },
      {
        "value": 4,
        "mean_risk": 0.48965517241379314,
        "count": 174,
        "score": 0.42204926108374385
      },
      {
        "value": 5,
        "mean_risk": 0.592156862745098,
        "count": 51,
        "score": 0.8320560224089635
      }
    ],
    "自我认同问题程度": [
      {
        "value": 0,
        "mean_risk": 0.3241706161137441,
        "count": 422,
        "score": -0.23988896411645233
      },
      {
        "value": 1,
        "mean_risk": 0.34094488188976374,
        "count": 508,
        "score": -0.17279190101237374
      },
      {
        "value": 2,
        "mean_risk": 0.3693679092382496,
        "count": 617,
        "score": -0.059099791618430375
      },
      {
        "value": 3,
        "mean_risk": 0.45473684210526316,
        "count": 285,
        "score": 0.28237593984962395
      },
      {
        "value": 4,
        "mean_risk": 0.516751269035533,
        "count": 197,
        "score": 0.5304336475707034
      },
      {
        "value": 5,
        "mean_risk": 0.5267605633802817,
        "count": 71,
        "score": 0.5704708249496979
      }
    ],
    "受不良同伴影响强度": [
      {
        "value": 0,
        "mean_risk": 0.32755555555555554,
        "count": 450,
        "score": -0.22634920634920652
      },
      {
        "value": 1,
        "mean_risk": 0.33664596273291925,
        "count": 483,
        "score": -0.18998757763975171
      },
      {
        "value": 2,
        "mean_risk": 0.37422512234910277,
        "count": 613,
        "score": -0.03967093917501763
      },
      {
        "value": 3,
        "mean_risk": 0.46702127659574466,
        "count": 282,
        "score": 0.33151367781154994
      },
      {
        "value": 4,
        "mean_risk": 0.5024509803921569,
        "count": 204,
        "score": 0.4732324929971987
      },
      {
        "value": 5,
        "mean_risk": 0.486764705882353,
        "count": 68,
        "score": 0.41048739495798325
      }
    ],
    "受社区影响强度": [
      {
        "value": 0,
        "mean_risk": 0.3133495145631068,
        "count": 412,
        "score": -0.2831733703190016
      },
      {
        "value": 1,
        "mean_risk": 0.34573643410852717,
        "count": 516,
        "score": -0.15362569213732002
      },
      {
        "value": 2,
        "mean_risk": 0.3722132471728595,
        "count": 619,
        "score": -0.047718439879990804
      },
      {
        "value": 3,
        "mean_risk": 0.47474747474747475,
        "count": 297,
        "score": 0.3624184704184703
      },
      {
        "value": 4,
        "mean_risk": 0.5061111111111111,
        "count": 180,
        "score": 0.48787301587301557
      },
      {
        "value": 5,
        "mean_risk": 0.4828947368421053,
        "count": 76,
        "score": 0.3950075187969926
      }
    ],
    "逃学旷课频次": [
      {
        "value": 0,
        "mean_risk": 0.2861507128309572,
        "count": 491,
        "score": -0.3919685772475998
      },
      {
        "value": 1,
        "mean_risk": 0.2805414551607445,
        "count": 591,
        "score": -0.4144056079284506
      },
      {
        "value": 2,
        "mean_risk": 0.4851020408163265,
        "count": 490,
        "score": 0.4038367346938774
      },
      {
        "value": 3,
        "mean_risk": 0.4587121212121212,
        "count": 264,
        "score": 0.29827705627705603
      },
      {
        "value": 4,
        "mean_risk": 0.5180094786729857,
        "count": 211,
        "score": 0.5354664861205143
      },
      {
        "value": 5,
        "mean_risk": 0.6094339622641509,
        "count": 53,
        "score": 0.901164420485175
      }
    ],
    "法治教育学习效果": [
      {
        "value": 0,
        "mean_risk": 0.526431718061674,
        "count": 227,
        "score": 0.5691554436752673
      },
      {
        "value": 1,
        "mean_risk": 0.5460264900662252,
        "count": 302,
        "score": 0.647534531693472
      },
      {
        "value": 2,
        "mean_risk": 0.4929742388758782,
        "count": 427,
        "score": 0.43532552693208415
      },
      {
        "value": 3,
        "mean_risk": 0.30201342281879195,
        "count": 447,
        "score": -0.3285177372962609
      },
      {
        "value": 4,
        "mean_risk": 0.29880668257756565,
        "count": 419,
        "score": -0.3413446982611661
      },
      {
        "value": 5,
        "mean_risk": 0.18561151079136692,
        "count": 278,
        "score": -0.794125385405961
      }
    ],
    "上网时间问题程度": [
      {
        "value": 0,
        "mean_risk": 0.32433734939759035,
        "count": 415,
        "score": -0.2392220309810673
      },
      {
        "value": 1,
        "mean_risk": 0.35422535211267603,
        "count": 568,
        "score": -0.11967002012072459
      },
      {
        "value": 2,
        "mean_risk": 0.3592783505154639,
        "count": 582,
        "score": -0.09945802650957303
      },
      {
        "value": 3,
        "mean_risk": 0.46942148760330576,
        "count": 242,
        "score": 0.34111452184179436
      },
      {
        "value": 4,
        "mean_risk": 0.529646017699115,
        "count": 226,
        "score": 0.5820126422250314
      },
      {
        "value": 5,
        "mean_risk": 0.4253731343283582,
        "count": 67,
        "score": 0.16492110874200416
      }
    ],
    "深夜上网问题程度": [
      {
        "value": 0,
        "mean_risk": 0.2817241379310345,
        "count": 580,
        "score": -0.40967487684729065
      },
      {
        "value": 1,
        "mean_risk": 0.30636942675159234,
        "count": 628,
        "score": -0.3110937215650593
      },
      {
        "value": 2,
        "mean_risk": 0.5004376367614879,
        "count": 457,
        "score": 0.46517911847452287
      },
      {
        "value": 3,
        "mean_risk": 0.5126168224299066,
        "count": 214,
        "score": 0.5138958611481976
      },
      {
        "value": 4,
        "mean_risk": 0.5023391812865498,
        "count": 171,
        "score": 0.4727852965747703
      },
      {
        "value": 5,
        "mean_risk": 0.532,
        "count": 50,
        "score": 0.5914285714285714
      }
    ],
    "接触有害内容频次": [
      {
        "value": 0,
        "mean_risk": 0.31102756892230576,
        "count": 399,
        "score": -0.29246115288220564
      },
      {
        "value": 1,
        "mean_risk": 0.35087378640776695,
        "count": 515,
        "score": -0.1330762829403609
      },
      {
        "value": 2,
        "mean_risk": 0.3632911392405063,
        "count": 632,
        "score": -0.08340687160940341
      },
      {
        "value": 3,
        "mean_risk": 0.472202166064982,
        "count": 277,
        "score": 0.3522372356884993
      },
      {
        "value": 4,
        "mean_risk": 0.512962962962963,
        "count": 216,
        "score": 0.5152804232804231
      },
      {
        "value": 5,
        "mean_risk": 0.5032786885245901,
        "count": 61,
        "score": 0.4765433255269318
      }
    ],
    "时间管理问题程度": [
      {
        "value": 0,
        "mean_risk": 0.3443609022556391,
        "count": 399,
        "score": -0.15912781954887234
      },
      {
        "value": 1,
        "mean_risk": 0.3497005988023952,
        "count": 501,
        "score": -0.13776903336184798
      },
      {
        "value": 2,
        "mean_risk": 0.34317460317460313,
        "count": 630,
        "score": -0.16387301587301617
      },
      {
        "value": 3,
        "mean_risk": 0.4629032258064516,
        "count": 310,
        "score": 0.3150414746543777
      },
      {
        "value": 4,
        "mean_risk": 0.515609756097561,
        "count": 205,
        "score": 0.5258675958188153
      },
      {
        "value": 5,
        "mean_risk": 0.5218181818181818,
        "count": 55,
        "score": 0.5507012987012987
      }
    ],
    "理财观念行为问题程度": [
      {
        "value": 0,
        "mean_risk": 0.31360544217687075,
        "count": 441,
        "score": -0.2821496598639457
      },
      {
        "value": 1,
        "mean_risk": 0.3483122362869198,
        "count": 474,
        "score": -0.14332248342374942
      },
      {
        "value": 2,
        "mean_risk": 0.367479674796748,
        "count": 615,
        "score": -0.06665272938443678
      },
      {
        "value": 3,
        "mean_risk": 0.46932907348242814,
        "count": 313,
        "score": 0.34074486535828385
      },
      {
        "value": 4,
        "mean_risk": 0.5133004926108374,
        "count": 203,
        "score": 0.516630541871921
      },
      {
        "value": 5,
        "mean_risk": 0.48518518518518516,
        "count": 54,
        "score": 0.40416931216931196
      }
    ],
    "情感支持": [
      {
        "value": 0,
        "mean_risk": 0.5195121951219512,
        "count": 205,
        "score": 0.5414773519163762
      },
      {
        "value": 1,
        "mean_risk": 0.5318318318318318,
        "count": 333,
        "score": 0.5907558987558985
      },
      {
        "value": 2,
        "mean_risk": 0.5031862745098039,
        "count": 408,
        "score": 0.47617366946778694
      },
      {
        "value": 3,
        "mean_risk": 0.3,
        "count": 459,
        "score": -0.33657142857142874
      },
      {
        "value": 4,
        "mean_risk": 0.29728506787330317,
        "count": 442,
        "score": -0.34743115707821604
      },
      {
        "value": 5,
        "mean_risk": 0.1924901185770751,
        "count": 253,
        "score": -0.7666109542631283
      }
    ],
    "情绪调节困难程度": [
      {
        "value": 0,
        "mean_risk": 0.33498694516971284,
        "count": 383,
        "score": -0.19662364789257736
      },
      {
        "value": 1,
        "mean_risk": 0.34793233082706765,
        "count": 532,
        "score": -0.1448421052631581
      },
      {
        "value": 2,
        "mean_risk": 0.34984756097560976,
        "count": 656,
        "score": -0.13718118466898965
      },
      {
        "value": 3,
        "mean_risk": 0.4860294117647058,
        "count": 272,
        "score": 0.4075462184873946
      },
      {
        "value": 4,
        "mean_risk": 0.5119402985074627,
        "count": 201,
        "score": 0.5111897654584221
      },
      {
        "value": 5,
        "mean_risk": 0.5125,
        "count": 56,
        "score": 0.5134285714285711
      }
    ]
  }
}